iceframe/__init__.py
iceframe/agent_cli.py
iceframe/async_ops.py
iceframe/branching.py
iceframe/cache.py
iceframe/catalog_ops.py
iceframe/cli.py
iceframe/compaction.py
iceframe/core.py
iceframe/datafusion_ops.py
iceframe/distributed.py
iceframe/evolution.py
iceframe/export.py
iceframe/expressions.py
iceframe/federation.py
iceframe/functions.py
iceframe/gc.py
iceframe/incremental.py
iceframe/ingest.py
iceframe/ingestion.py
iceframe/magics.py
iceframe/maintenance.py
iceframe/mcp_server.py
iceframe/memory.py
iceframe/monitoring.py
iceframe/mor.py
iceframe/namespace.py
iceframe/operations.py
iceframe/optimizer.py
iceframe/parallel.py
iceframe/partition.py
iceframe/pool.py
iceframe/procedures.py
iceframe/pydantic.py
iceframe/quality.py
iceframe/query.py
iceframe/rollback.py
iceframe/schema.py
iceframe/skipping.py
iceframe/stats.py
iceframe/streaming.py
iceframe/utils.py
iceframe/views.py
iceframe/visualization.py
iceframe/agent/__init__.py
iceframe/agent/core.py
iceframe/agent/llm_anthropic.py
iceframe/agent/llm_base.py
iceframe/agent/llm_gemini.py
iceframe/agent/llm_openai.py
iceframe/agent/tools.py
iceframe-0.10.0.dist-info/METADATA
iceframe-0.10.0.dist-info/WHEEL
iceframe-0.10.0.dist-info/entry_points.txt
iceframe-0.10.0.dist-info/top_level.txt
iceframe-0.10.0.dist-info/RECORD
