Metadata-Version: 2.4
Name: iceframe
Version: 0.10.0
Summary: A DataFrame-like library for working with Apache Iceberg tables
Author-email: Alex Merced <alex@alexmerced.com>
License: Apache-2.0
Project-URL: Homepage, https://github.com/alexmerced/iceframe
Project-URL: Documentation, https://github.com/alexmerced/iceframe/tree/main/docs
Project-URL: Repository, https://github.com/alexmerced/iceframe
Project-URL: Issues, https://github.com/alexmerced/iceframe/issues
Keywords: iceberg,dataframe,data engineering,apache iceberg
Classifier: Development Status :: 3 - Alpha
Classifier: Intended Audience :: Developers
Classifier: License :: OSI Approved :: Apache Software License
Classifier: Programming Language :: Python :: 3
Classifier: Programming Language :: Python :: 3.9
Classifier: Programming Language :: Python :: 3.10
Classifier: Programming Language :: Python :: 3.11
Classifier: Programming Language :: Python :: 3.12
Classifier: Topic :: Software Development :: Libraries :: Python Modules
Requires-Python: >=3.9
Requires-Dist: pyiceberg>=0.6.0
Requires-Dist: pyarrow>=14.0.0
Requires-Dist: polars>=0.19.0
Requires-Dist: python-dotenv>=1.0.0
Requires-Dist: pandas>=2.0.0
Provides-Extra: aws
Requires-Dist: s3fs>=2023.1.0; extra == "aws"
Requires-Dist: boto3>=1.28.0; extra == "aws"
Provides-Extra: gcs
Requires-Dist: gcsfs>=2023.1.0; extra == "gcs"
Provides-Extra: azure
Requires-Dist: adlfs>=2023.1.0; extra == "azure"
Provides-Extra: all
Requires-Dist: iceframe[aws]; extra == "all"
Requires-Dist: iceframe[gcs]; extra == "all"
Requires-Dist: iceframe[azure]; extra == "all"
Requires-Dist: iceframe[delta]; extra == "all"
Requires-Dist: iceframe[lance]; extra == "all"
Requires-Dist: iceframe[vortex]; extra == "all"
Requires-Dist: iceframe[excel]; extra == "all"
Requires-Dist: iceframe[gsheets]; extra == "all"
Requires-Dist: iceframe[hudi]; extra == "all"
Requires-Dist: iceframe[sql]; extra == "all"
Requires-Dist: iceframe[xml]; extra == "all"
Requires-Dist: iceframe[stats]; extra == "all"
Requires-Dist: iceframe[api]; extra == "all"
Requires-Dist: iceframe[hf]; extra == "all"
Requires-Dist: iceframe[html]; extra == "all"
Requires-Dist: iceframe[clipboard]; extra == "all"
Requires-Dist: python-dotenv>=1.0.0; extra == "all"
Provides-Extra: dev
Requires-Dist: pytest>=7.0.0; extra == "dev"
Requires-Dist: pytest-cov>=4.0.0; extra == "dev"
Requires-Dist: pytest-asyncio>=0.21.0; extra == "dev"
Requires-Dist: black>=23.0.0; extra == "dev"
Requires-Dist: ruff>=0.0.270; extra == "dev"
Requires-Dist: mypy>=1.3.0; extra == "dev"
Requires-Dist: python-dotenv>=1.0.0; extra == "dev"
Provides-Extra: pdf
Requires-Dist: fpdf2>=2.7.0; extra == "pdf"
Requires-Dist: markdown-it-py>=3.0.0; extra == "pdf"
Provides-Extra: delta
Requires-Dist: deltalake>=0.15.0; extra == "delta"
Provides-Extra: lance
Requires-Dist: pylance>=0.9.0; extra == "lance"
Provides-Extra: vortex
Requires-Dist: vortex-data>=0.1.0; extra == "vortex"
Provides-Extra: excel
Requires-Dist: fastexcel>=0.9.0; extra == "excel"
Provides-Extra: gsheets
Requires-Dist: gspread>=6.0.0; extra == "gsheets"
Provides-Extra: hudi
Requires-Dist: getdaft>=0.2.0; extra == "hudi"
Provides-Extra: mcp
Requires-Dist: mcp>=0.1.0; extra == "mcp"
Provides-Extra: ingestion
Requires-Dist: iceframe[delta,excel,gsheets,hudi,lance,vortex]; extra == "ingestion"
Provides-Extra: cli
Requires-Dist: typer>=0.9.0; extra == "cli"
Requires-Dist: rich>=13.0.0; extra == "cli"
Provides-Extra: agent
Requires-Dist: openai>=1.0.0; extra == "agent"
Requires-Dist: anthropic>=0.18.0; extra == "agent"
Requires-Dist: google-generativeai>=0.3.0; extra == "agent"
Requires-Dist: rich>=13.0.0; extra == "agent"
Provides-Extra: cache
Requires-Dist: diskcache>=5.6.0; extra == "cache"
Provides-Extra: streaming
Requires-Dist: kafka-python>=2.0.0; extra == "streaming"
Provides-Extra: monitoring
Requires-Dist: psutil>=5.9.0; extra == "monitoring"
Requires-Dist: prometheus-client>=0.19.0; extra == "monitoring"
Provides-Extra: notebook
Requires-Dist: ipython>=8.0.0; extra == "notebook"
Requires-Dist: ipywidgets>=8.0.0; extra == "notebook"
Provides-Extra: pydantic
Requires-Dist: pydantic>=2.0.0; extra == "pydantic"
Provides-Extra: sql
Requires-Dist: connectorx>=0.3.0; extra == "sql"
Requires-Dist: sqlalchemy>=2.0.0; extra == "sql"
Provides-Extra: xml
Requires-Dist: lxml>=4.9.0; extra == "xml"
Provides-Extra: stats
Requires-Dist: pyreadstat; extra == "stats"
Provides-Extra: api
Requires-Dist: requests; extra == "api"
Provides-Extra: hf
Requires-Dist: datasets; extra == "hf"
Provides-Extra: html
Requires-Dist: lxml; extra == "html"
Requires-Dist: html5lib; extra == "html"
Requires-Dist: beautifulsoup4; extra == "html"
Provides-Extra: clipboard
Requires-Dist: pyperclip; extra == "clipboard"
Provides-Extra: datafusion
Requires-Dist: datafusion>=35.0.0; extra == "datafusion"
Provides-Extra: distributed
Requires-Dist: ray>=2.0.0; extra == "distributed"
Provides-Extra: viz
Requires-Dist: altair>=5.0.0; extra == "viz"
